auth/__init__.py
auth/eop_signature.py
auth/signature.py
billing/__init__.py
billing/client.py
billing/commands.py
cce/__init__.py
cce/client.py
cce/commands.py
cda/__init__.py
cda/client.py
cda/commands.py
cli/__init__.py
cli/main.py
config/__init__.py
config/settings.py
core/__init__.py
ctyun_cli/__init__.py
ctyun_cli-1.7.15.dist-info/licenses/LICENSE
ebs/__init__.py
ebs/client.py
ebs/commands.py
ecs/__init__.py
ecs/client.py
ecs/commands.py
elb/__init__.py
elb/client.py
elb/commands.py
iam/__init__.py
iam/client.py
iam/commands.py
monitor/__init__.py
monitor/client.py
monitor/commands.py
redis/__init__.py
redis/client.py
redis/commands.py
security/__init__.py
security/client.py
security/commands.py
utils/__init__.py
utils/cache.py
utils/helpers.py
vpc/__init__.py
vpc/client.py
vpc/commands.py
ctyun_cli-1.7.15.dist-info/METADATA
ctyun_cli-1.7.15.dist-info/WHEEL
ctyun_cli-1.7.15.dist-info/entry_points.txt
ctyun_cli-1.7.15.dist-info/top_level.txt
ctyun_cli-1.7.15.dist-info/RECORD
