Metadata-Version: 2.4
Name: ctyun-cli
Version: 1.7.15
Summary: 天翼云CLI工具 - 基于终端的云资源管理平台
Home-page: https://github.com/fengyucn/ctyun-cli
Author: Y.FENG
Author-email: "Y.FENG" <popfrog@gmail.com>
Maintainer: Y.FENG
Maintainer-email: "Y.FENG" <popfrog@gmail.com>
License: MIT
Project-URL: Homepage, https://pypi.org/project/ctyun-cli/
Project-URL: Documentation, https://github.com/fengyucn/ctyun-cli
Project-URL: Repository, https://github.com/fengyucn/ctyun-cli
Project-URL: Bug Tracker, https://github.com/fengyucn/ctyun-cli/issues
Project-URL: Changelog, https://github.com/fengyucn/ctyun-cli/commits/master
Keywords: ctyun,cloud,cli,management,monitoring,ecs,redis,distributed-cache,query,snapshot,keypair,volume,backup,affinity-group,flavor,resize,vnc,statistics,api,devops,cda,cloud-dedicated-access,专线,网关,vpc,health-check,link-probe
Platform: any
Classifier: Development Status :: 4 - Beta
Classifier: Intended Audience :: Developers
Classifier: Intended Audience :: System Administrators
Classifier: Operating System :: OS Independent
Classifier: Programming Language :: Python :: 3
Classifier: Programming Language :: Python :: 3.8
Classifier: Programming Language :: Python :: 3.9
Classifier: Programming Language :: Python :: 3.10
Classifier: Programming Language :: Python :: 3.11
Classifier: Programming Language :: Python :: 3.12
Classifier: Topic :: System :: Systems Administration
Classifier: Topic :: Utilities
Classifier: Topic :: Internet :: WWW/HTTP
Classifier: Environment :: Console
Requires-Python: >=3.8
License-File: LICENSE
Requires-Dist: requests>=2.31.0
Requires-Dist: click>=8.1.0
Requires-Dist: cryptography>=41.0.0
Requires-Dist: colorama>=0.4.6
Requires-Dist: tabulate>=0.9.0
Requires-Dist: pyyaml>=6.0
Provides-Extra: dev
Requires-Dist: pytest>=7.4.0; extra == "dev"
Requires-Dist: pytest-cov>=4.1.0; extra == "dev"
Requires-Dist: black>=23.0.0; extra == "dev"
Requires-Dist: flake8>=6.0.0; extra == "dev"
Requires-Dist: build>=0.10.0; extra == "dev"
Requires-Dist: twine>=4.0.0; extra == "dev"
Provides-Extra: test
Requires-Dist: pytest>=7.4.0; extra == "test"
Requires-Dist: pytest-cov>=4.1.0; extra == "test"
Provides-Extra: lint
Requires-Dist: black>=23.0.0; extra == "lint"
Requires-Dist: flake8>=6.0.0; extra == "lint"
Provides-Extra: build
Requires-Dist: build>=0.10.0; extra == "build"
Requires-Dist: twine>=4.0.0; extra == "build"
Dynamic: author
Dynamic: home-page
Dynamic: license-file
Dynamic: maintainer
Dynamic: platform
Dynamic: requires-python
